cataloguer/__init__.py
cataloguer/cli.py
cataloguer/console/__init__.py
cataloguer/console/default.py
cataloguer/console/output.py
cataloguer/console/tree.py
cataloguer/filesystem/__init__.py
cataloguer/filesystem/directory.py
cataloguer/filesystem/file.py
cataloguer/filesystem/metadata.py
cataloguer/filesystem/utils.py
cataloguer/settings.py
cataloguer/storage.py
cataloguer-2.2.dist-info/LICENSE
cataloguer-2.2.dist-info/METADATA
cataloguer-2.2.dist-info/WHEEL
cataloguer-2.2.dist-info/entry_points.txt
cataloguer-2.2.dist-info/RECORD
