Metadata-Version: 2.1
Name: cataloguer
Version: 2.2
Summary: Organize your media files
Home-page: https://github.com/iago1460/cataloguer
License: MIT
Author: Iago Veloso
Requires-Python: >=3.9
Classifier: Development Status :: 5 - Production/Stable
Classifier: Environment :: Console
Classifier: Intended Audience :: End Users/Desktop
Classifier: License :: OSI Approved :: MIT License
Classifier: Operating System :: OS Independent
Classifier: Programming Language :: Python :: 3
Classifier: Programming Language :: Python :: 3.9
Classifier: Programming Language :: Python :: 3.10
Classifier: Programming Language :: Python :: 3.11
Classifier: Topic :: Software Development :: Build Tools
Classifier: Topic :: Software Development :: Libraries :: Python Modules
Requires-Dist: Pillow (==8.1.2)
Requires-Dist: click (>=8.1.3,<9.0.0)
Requires-Dist: pydantic (>=1.10.5,<2.0.0)
Requires-Dist: python-dateutil (==2.8.2)
Requires-Dist: python-magic (==0.4.27)
Requires-Dist: rich-click (>=1.6.1,<2.0.0)
Project-URL: Repository, https://github.com/iago1460/cataloguer
